{
  "version": "6",
  "dialect": "postgresql",
  "entries": [
    {
      "idx": 0,
      "version": "6",
      "when": 1715417734126,
      "tag": "0000_mysterious_shiver_man",
      "breakpoints": true
    },
    {
      "idx": 1,
      "version": "6",
      "when": 1715417764127,
      "tag": "0001_demonic_tana_nile",
      "breakpoints": true
    },
    {
      "idx": 2,
      "version": "6",
      "when": 1715417816138,
      "tag": "0002_same_wind_dancer",
      "breakpoints": true
    }
  ]
}